textforge/__init__.py
textforge/base.py
textforge/deployment.py
textforge/pipeline.py
textforge/quantize.py
textforge/serve.py
textforge/static/css/style.css
textforge/synthetic.py
textforge/templates/index.html
textforge/train.py
textforge/utils.py
textforge-0.1.2.dist-info/LICENSE
textforge-0.1.2.dist-info/METADATA
textforge-0.1.2.dist-info/WHEEL
textforge-0.1.2.dist-info/RECORD
