Metadata-Version: 2.3
Name: textforge
Version: 0.1.2
Summary: Automated Synthetic Data Generation, Distillation, Quantization and Deployment Pipeline.
License: MIT
Author: ameen-91
Author-email: mohammedameen9011@gmail.com
Requires-Python: >=3.11,<4.0
Classifier: License :: OSI Approved :: MIT License
Classifier: Programming Language :: Python :: 3
Classifier: Programming Language :: Python :: 3.11
Classifier: Programming Language :: Python :: 3.12
Classifier: Programming Language :: Python :: 3.13
Requires-Dist: datasets (>=3.2.0,<4.0.0)
Requires-Dist: evaluate (>=0.4.3,<0.5.0)
Requires-Dist: fastapi[standard] (>=0.115.8,<0.116.0)
Requires-Dist: google-genai (>=1.2.0,<2.0.0)
Requires-Dist: ipywidgets (>=8.1.5,<9.0.0)
Requires-Dist: jinja2 (>=3.1.5,<4.0.0)
Requires-Dist: onnx (>=1.17.0,<2.0.0)
Requires-Dist: onnxruntime (>=1.20.1,<2.0.0)
Requires-Dist: openai (>=1.63.0,<2.0.0)
Requires-Dist: pandas (==2.2.2)
Requires-Dist: peft (>=0.14.0,<0.15.0)
Requires-Dist: pytest (>=8.3.4,<9.0.0)
Requires-Dist: python-dotenv (>=1.0.1,<2.0.0)
Requires-Dist: scikit-learn (>=1.6.1,<2.0.0)
Requires-Dist: seaborn (>=0.13.2,<0.14.0)
Requires-Dist: tqdm (>=4.67.1,<5.0.0)
Requires-Dist: transformers (>=4.48.3,<5.0.0)
Requires-Dist: typer (>=0.15.1,<0.16.0)
